pf_sqlalchemy/__init__.py
pf_sqlalchemy/crud/__init__.py
pf_sqlalchemy/crud/pfs_crud_exception.py
pf_sqlalchemy/crud/pfs_crud_service.py
pf_sqlalchemy/crud/pfs_rest_helper_service.py
pf_sqlalchemy/db/__init__.py
pf_sqlalchemy/db/orm.py
flask_pf_sqlalchemy-1.0.dist-info/LICENSE
flask_pf_sqlalchemy-1.0.dist-info/METADATA
flask_pf_sqlalchemy-1.0.dist-info/WHEEL
flask_pf_sqlalchemy-1.0.dist-info/top_level.txt
flask_pf_sqlalchemy-1.0.dist-info/RECORD
