Metadata-Version: 2.1
Name: flask-pf-sqlalchemy
Version: 1.0
Summary: This is Flask Problem Fighter SQLAlchemy Extension
Home-page: https://github.com/problemfighter/flask-pf-sqlalchemy
Author: Touhid Mia
Author-email: hmtm.cse@gmail.com
License: Apache 2.0
Platform: any
Classifier: Environment :: Web Environment
Classifier: Intended Audience :: Developers
Classifier: License :: OSI Approved :: Apache Software License
Classifier: Operating System :: OS Independent
Classifier: Programming Language :: Python
Classifier: Topic :: Internet :: WWW/HTTP :: Dynamic Content
Classifier: Topic :: Software Development :: Libraries :: Python Modules
Requires-Dist: Flask
Requires-Dist: Flask-SQLAlchemy
